odoo10_addon_shopinvader_lead-10.0.1.0.2-nspkg.pth
odoo/addons/shopinvader_lead/README.rst
odoo/addons/shopinvader_lead/__init__.py
odoo/addons/shopinvader_lead/__manifest__.py
odoo/addons/shopinvader_lead/demo/email_demo.xml
odoo/addons/shopinvader_lead/demo/notification_demo.xml
odoo/addons/shopinvader_lead/models/__init__.py
odoo/addons/shopinvader_lead/models/lead.py
odoo/addons/shopinvader_lead/models/notification.py
odoo/addons/shopinvader_lead/readme/CONFIGURATION.rst
odoo/addons/shopinvader_lead/readme/CONTRIBUTORS.rst
odoo/addons/shopinvader_lead/readme/CREDITS.rst
odoo/addons/shopinvader_lead/readme/DESCRIPTION.rst
odoo/addons/shopinvader_lead/readme/ROADMAP.rst
odoo/addons/shopinvader_lead/services/__init__.py
odoo/addons/shopinvader_lead/services/lead.py
odoo/addons/shopinvader_lead/static/description/index.html
odoo/addons/shopinvader_lead/tests/__init__.py
odoo/addons/shopinvader_lead/tests/test_lead.py
odoo10_addon_shopinvader_lead-10.0.1.0.2.dist-info/METADATA
odoo10_addon_shopinvader_lead-10.0.1.0.2.dist-info/WHEEL
odoo10_addon_shopinvader_lead-10.0.1.0.2.dist-info/namespace_packages.txt
odoo10_addon_shopinvader_lead-10.0.1.0.2.dist-info/top_level.txt
odoo10_addon_shopinvader_lead-10.0.1.0.2.dist-info/RECORD
